QuantumInformation/RecurNum.py
QuantumInformation/__init__.py
QuantumInformation/chap2_nutsboltsquantum.py
QuantumInformation/chap3_linearalgebra.py
QuantumInformation/chap4_quantumtools.py
QuantumInformation/chap5_partial_quantumentanglement.py
QuantumInformation/chap6_hamiltonians.py
QuantumInformation/chap7_randommatrix.py
QuantumInformation-1.2.dist-info/METADATA
QuantumInformation-1.2.dist-info/WHEEL
QuantumInformation-1.2.dist-info/top_level.txt
QuantumInformation-1.2.dist-info/RECORD
