Metadata-Version: 2.1
Name: QuantumInformation
Version: 1.2
Summary: Quantum Information and Computation package
Author: M. S. Ramkarthik and Pranay Barkataki
Requires-Python: >= 3.7.9
Requires-Dist: numpy (>=1.25.2)
Requires-Dist: scipy (>=1.11.1)
Provides-Extra: dev
Requires-Dist: pytest (>=7.0) ; extra == 'dev'
Requires-Dist: twine (>=4.0.2) ; extra == 'dev'
